darknet/__init__.py
darknet/file/__init__.py
darknet/file/file.py
darknet/file/fileencoding.py
darknet/image/__init__.py
darknet/image/encoding.py
darknet/network/__init__.py
darknet/network/network.py
darknet/text/__init__.py
darknet-0.3.dist-info/DESCRIPTION.rst
darknet-0.3.dist-info/METADATA
darknet-0.3.dist-info/RECORD
darknet-0.3.dist-info/WHEEL
darknet-0.3.dist-info/metadata.json
darknet-0.3.dist-info/top_level.txt
