Metadata-Version: 1.1
Name: darknet
Version: 0.3
Summary: basic package for using
Home-page: UNKNOWN
Author: wangjj
Author-email: hzwangjj@gmail.com
License: MIT License
Keywords: basic tools,utils
Platform: any
Classifier: Development Status :: 3 - Alpha
Classifier: Intended Audience :: Developers
Classifier: Topic :: Software Development :: Libraries
Classifier: License :: OSI Approved :: MIT License
Classifier: Programming Language :: Python :: 3
Classifier: Programming Language :: Python :: 3.5
